rtsdkdev/__init__.py
rtsdkdev/rpc.py
rtsdkdev/utils/api.py
rtsdkdev/utils/errors.py
rtsdkdev/utils/helpers.py
rtsdkdev/utils/logger.py
rtsdkdev/utils/polling.py
rtsdkdev/utils/schema.py
rtsdkdev/utils/types.py
rtsdkdev/version.py
rtsdkdev-0.1.8.dist-info/METADATA
rtsdkdev-0.1.8.dist-info/WHEEL
rtsdkdev-0.1.8.dist-info/RECORD
