Metadata-Version: 2.1
Name: rtsdkdev
Version: 0.1.8
Summary: Python package for Retool RPC
Home-page: https://retool.com
License: MIT
Author: huytool157
Author-email: pham@retool.com
Requires-Python: >=3.10,<4.0
Classifier: License :: OSI Approved :: MIT License
Classifier: Programming Language :: Python :: 3
Classifier: Programming Language :: Python :: 3.10
Classifier: Programming Language :: Python :: 3.11
Requires-Dist: asyncio (>=3.4.3,<4.0.0)
Requires-Dist: httpx (>=0.25.0,<0.26.0)
Project-URL: Repository, https://github.com/tryretool/rtsdk
